.editorconfig
.gitignore
.nojekyll
.travis.yml
AUTHORS.rst
CONTRIBUTING.rst
HISTORY.rst
LICENSE
MANIFEST.in
Makefile
README.rst
index.html
notes.txt
requirements_dev.txt
setup.cfg
setup.py
tox.ini
.github/ISSUE_TEMPLATE.md
.vscode/settings.json
docs/Makefile
docs/authors.rst
docs/conf.erc
docs/conf.py
docs/contributing.rst
docs/history.rst
docs/index.rst
docs/installation.rst
docs/make.bat
docs/readme.rst
docs/usage.md
docs/_build/doctrees/authors.doctree
docs/_build/doctrees/contributing.doctree
docs/_build/doctrees/environment.pickle
docs/_build/doctrees/history.doctree
docs/_build/doctrees/index.doctree
docs/_build/doctrees/installation.doctree
docs/_build/doctrees/readme.doctree
docs/_build/doctrees/usage.doctree
docs/_build/singlehtml/.buildinfo
docs/_build/singlehtml/.nojekyll
docs/_build/singlehtml/index.html
docs/_build/singlehtml/objects.inv
docs/_build/singlehtml/_images/zyc-fp-search-results.png
docs/_build/singlehtml/_images/zyc-part-fp-copy.png
docs/_build/singlehtml/_images/zyc-part-search-results.png
docs/_build/singlehtml/_images/zyc-part-search-terms.png
docs/_build/singlehtml/_images/zyc-path-setup.png
docs/_build/singlehtml/_images/zyc-pin-copy.png
docs/_build/singlehtml/_images/zyc-pin-sort.png
docs/_build/singlehtml/_images/zyc.png
docs/_build/singlehtml/_static/alabaster.css
docs/_build/singlehtml/_static/basic.css
docs/_build/singlehtml/_static/custom.css
docs/_build/singlehtml/_static/doctools.js
docs/_build/singlehtml/_static/documentation_options.js
docs/_build/singlehtml/_static/file.png
docs/_build/singlehtml/_static/jquery-3.2.1.js
docs/_build/singlehtml/_static/jquery.js
docs/_build/singlehtml/_static/language_data.js
docs/_build/singlehtml/_static/minus.png
docs/_build/singlehtml/_static/plus.png
docs/_build/singlehtml/_static/pygments.css
docs/_build/singlehtml/_static/searchtools.js
docs/_build/singlehtml/_static/underscore-1.3.1.js
docs/_build/singlehtml/_static/underscore.js
docs/images/zyc-fp-search-results.png
zyc.egg-info/PKG-INFO
zyc.egg-info/SOURCES.txt
zyc.egg-info/dependency_links.txt
zyc.egg-info/entry_points.txt
zyc.egg-info/not-zip-safe
zyc.egg-info/requires.txt
zyc.egg-info/top_level.txt