Metadata-Version: 2.1
Name: zyc
Version: 1.0.0
Summary: A GUI for searching and selecting parts and footprints for use in SKiDL.
Home-page: https://github.com/devbisme/zyc
Author: Dave Vandenbout
Author-email: devbisme@xess.com
License: MIT license
Keywords: zyc
Platform: UNKNOWN
Classifier: Development Status :: 5 - Production/Stable
Classifier: Intended Audience :: Manufacturing
Classifier: License :: OSI Approved :: MIT License
Classifier: Natural Language :: English
Classifier: Operating System :: OS Independent
Classifier: Programming Language :: Python :: 2.7
Classifier: Programming Language :: Python :: 3
Classifier: Topic :: Scientific/Engineering :: Electronic Design Automation (EDA)
License-File: LICENSE
License-File: AUTHORS.rst
